ultima_scraper_api/.readthedocs.yaml
ultima_scraper_api/__init__.py
ultima_scraper_api/__main__.py
ultima_scraper_api/apis/__init__.py
ultima_scraper_api/apis/api_helper.py
ultima_scraper_api/apis/api_streamliner.py
ultima_scraper_api/apis/auth_streamliner.py
ultima_scraper_api/apis/background_tasks.py
ultima_scraper_api/apis/fansly/__init__.py
ultima_scraper_api/apis/fansly/authenticator.py
ultima_scraper_api/apis/fansly/classes/__init__.py
ultima_scraper_api/apis/fansly/classes/auth_model.py
ultima_scraper_api/apis/fansly/classes/collection_model.py
ultima_scraper_api/apis/fansly/classes/comment_model.py
ultima_scraper_api/apis/fansly/classes/extras.py
ultima_scraper_api/apis/fansly/classes/hightlight_model.py
ultima_scraper_api/apis/fansly/classes/message_model.py
ultima_scraper_api/apis/fansly/classes/post_model.py
ultima_scraper_api/apis/fansly/classes/story_model.py
ultima_scraper_api/apis/fansly/classes/subscription_model.py
ultima_scraper_api/apis/fansly/classes/user_model.py
ultima_scraper_api/apis/fansly/decorators/decorators.py
ultima_scraper_api/apis/fansly/fansly.py
ultima_scraper_api/apis/loyalfans/authenticator.py
ultima_scraper_api/apis/loyalfans/classes/__init__.py
ultima_scraper_api/apis/loyalfans/classes/auth_model.py
ultima_scraper_api/apis/loyalfans/classes/extras.py
ultima_scraper_api/apis/loyalfans/classes/message_model.py
ultima_scraper_api/apis/loyalfans/classes/post_model.py
ultima_scraper_api/apis/loyalfans/classes/user_model.py
ultima_scraper_api/apis/loyalfans/loyalfans.py
ultima_scraper_api/apis/onlyfans/__init__.py
ultima_scraper_api/apis/onlyfans/authenticator.py
ultima_scraper_api/apis/onlyfans/classes/__init__.py
ultima_scraper_api/apis/onlyfans/classes/auth_model.py
ultima_scraper_api/apis/onlyfans/classes/chat_model.py
ultima_scraper_api/apis/onlyfans/classes/comment_model.py
ultima_scraper_api/apis/onlyfans/classes/extras.py
ultima_scraper_api/apis/onlyfans/classes/hightlight_model.py
ultima_scraper_api-2.2.45.dist-info/LICENSE
ultima_scraper_api-2.2.45.dist-info/METADATA
ultima_scraper_api-2.2.45.dist-info/WHEEL
ultima_scraper_api-2.2.45.dist-info/RECORD
