Metadata-Version: 2.3
Name: ultima-scraper-api
Version: 2.2.45
Summary: 
Author: UltimaHoarder
Author-email: 1285176+UltimaHoarder@users.noreply.github.com
Requires-Python: >=3.10,<4.0
Classifier: Programming Language :: Python :: 3
Classifier: Programming Language :: Python :: 3.10
Classifier: Programming Language :: Python :: 3.11
Classifier: Programming Language :: Python :: 3.12
Classifier: Programming Language :: Python :: 3.13
Provides-Extra: dev
Requires-Dist: Sphinx (>=5.3.0) ; extra == "dev"
Requires-Dist: aiofiles (>=22.1.0)
Requires-Dist: aiohttp (>=3.8.4)
Requires-Dist: aiohttp-socks (>=0.9.0)
Requires-Dist: alive-progress (>=3.1.5)
Requires-Dist: beautifulsoup4 (>=4.11.1)
Requires-Dist: black (>=23.3.0) ; extra == "dev"
Requires-Dist: dill (>=0.3.6)
Requires-Dist: httpx (>=0.28)
Requires-Dist: inflection (>=0.5.1)
Requires-Dist: lxml (>=4.9.1)
Requires-Dist: mergedeep (>=1.3.4)
Requires-Dist: mypy (>=0.991)
Requires-Dist: orjson (>=3.8.3)
Requires-Dist: pydantic (>=2.0)
Requires-Dist: python-dateutil (>=2.8.2)
Requires-Dist: python-semantic-release (>=7.33.2) ; extra == "dev"
Requires-Dist: python-socks[asyncio] (>=2.2.0)
Requires-Dist: pywidevine (>=1.8.0)
Requires-Dist: requests[socks] (>=2.28)
Requires-Dist: sphinx-autoapi (>=2.0.0) ; extra == "dev"
Requires-Dist: sphinx-rtd-theme (>=1.1.1) ; extra == "dev"
Requires-Dist: user-agent (>=0.1.10)
Requires-Dist: websockets (>=15.0.1,<16.0.0)
Requires-Dist: win32-setctime (>=1.1.0) ; platform_system == "Windows"
Requires-Dist: xmltodict (>=0.13.0)
Project-URL: Homepage, https://github.com/UltimaHoarder/UltimaScraperAPI
